Metadata-Version: 2.1
Name: mtgx2nx
Version: 0.0.1
Summary: Maltego file transformer, Using networkx.
Home-page: https://github.com/Woniuke/mtgx2nx/
Author: Woniuke
Author-email: liutonggit@163.com
License: MIT
Platform: UNKNOWN
Classifier: Programming Language :: Python :: 3
Classifier: License :: OSI Approved :: MIT License
Classifier: Operating System :: OS Independent
Requires-Python: >=3.6
License-File: LICENSE
